pyllk/__init__.py
pyllk/grammar.py
pyllk/parser.py
pyllk/production_rule.py
pyllk/token.py
pyllk/token_stream.py
pyllk/ebnf/__init__.py
pyllk/ebnf/decoder.py
pyllk/ebnf/parser.py
pyllk/ebnf/parsetab.py
pyllk/ebnf/resolver.py
pyllk/experiments/__init__.py
pyllk/experiments/spacy.py
pyllk-0.0.13.dist-info/LICENSE.txt
pyllk-0.0.13.dist-info/METADATA
pyllk-0.0.13.dist-info/WHEEL
pyllk-0.0.13.dist-info/top_level.txt
pyllk-0.0.13.dist-info/RECORD
