Metadata-Version: 2.1
Name: pyllk
Version: 0.0.13
Summary: A python LL(k) parser with a twist where tokens can be any arbitrary objects.
Home-page: https://gitlab.com/majorspot/libraries/pyllk
Author: Michael Privat
Author-email: mprivat@majorspot.com
License: MIT
Keywords: parser ll(k) lex yacc
Platform: UNKNOWN
Classifier: Development Status :: 3 - Alpha
Classifier: Intended Audience :: Developers
Classifier: Intended Audience :: Information Technology
Classifier: License :: OSI Approved :: MIT License
Classifier: Programming Language :: Python
Classifier: Programming Language :: Python :: 3.6
Classifier: Programming Language :: Python :: 3.7
Classifier: Programming Language :: Python :: 3.8
Requires-Python: >=3.6
